arduino_temperature_sensors/ArduinoBoard.py
arduino_temperature_sensors/Daemon.py
arduino_temperature_sensors/Monitor.py
arduino_temperature_sensors/__init__.py
arduino_temperature_sensors/__main__.py
arduino_temperature_sensors/__project__.py
arduino_temperature_sensors/arduino_temperature_sensors.py
arduino_temperature_sensors-0.1.0.dist-info/LICENSE.md
arduino_temperature_sensors-0.1.0.dist-info/METADATA
arduino_temperature_sensors-0.1.0.dist-info/WHEEL
arduino_temperature_sensors-0.1.0.dist-info/entry_points.txt
arduino_temperature_sensors-0.1.0.dist-info/top_level.txt
arduino_temperature_sensors-0.1.0.dist-info/RECORD
