Metadata-Version: 2.1
Name: arduino-temperature-sensors
Version: 0.1.0
Summary: Readout software for the EPIC Arduino Temperature Sensors
Home-page: https://gitlab.ethz.ch/exotic-matter/cw-beam/arduino_temperature_sensors
Author: Carlos Vigo
Author-email: <carlosv@phys.ethz.ch>
License: GPLv3
Platform: UNKNOWN
Classifier: Programming Language :: Python :: 3.6
Classifier: License :: OSI Approved :: GNU General Public License v3 (GPLv3)
Classifier: Operating System :: POSIX :: Linux
Requires-Python: >=3.6
Requires-Dist: lab-utils
Requires-Dist: pyserial
Requires-Dist: zc.lockfile
Provides-Extra: dev
Requires-Dist: flake8 ; extra == 'dev'
Requires-Dist: pytest ; extra == 'dev'
Provides-Extra: docs
Requires-Dist: recommonmark ; extra == 'docs'
Requires-Dist: sphinx ; extra == 'docs'
Requires-Dist: sphinx-paramlinks ; extra == 'docs'
Requires-Dist: sphinx-rtd-theme ; extra == 'docs'
Requires-Dist: wheel ; extra == 'docs'
